fumoAPI/__init__.py
fumoAPI/fumoAPI.py
fumoAPI-1.3.dist-info/METADATA
fumoAPI-1.3.dist-info/WHEEL
fumoAPI-1.3.dist-info/top_level.txt
fumoAPI-1.3.dist-info/RECORD
