Metadata-Version: 2.1
Name: fumoAPI
Version: 1.3
Summary: Simple API wrapper for https://fumos.live
Home-page: https://github.com/Airiuwu/fumoAPI
Author: Adobee
Author-email: Adobe@katsumi.cf
License: MIT
Download-URL: https://pypi.org/project/fumoAPI/
Keywords: fumoAPI
Platform: UNKNOWN
Requires-Dist: aiohttp
Requires-Dist: requests
